{"version":1,"timescale":30000,"offset":0,"framerate":29.97,"width":1920,"height":1080,"totalDuration":2043000,"fragments":[{"start":0,"duration":70070,"interval":14014,"events":[[{"region":{"language":"German","orientation":"Up","lines":[{"text":"DEVcon","left":793,"top":226,"width":148,"height":39,"word":[{"text":"DEVcon","left":793,"top":226,"width":148,"height":39,"confidence":608}]},{"text":"02.2019","left":821,"top":276,"width":98,"height":28,"word":[{"text":"02.2019","left":821,"top":276,"width":98,"height":28,"confidence":302}]}]}}],[],[{"region":{"language":"Finnish","orientation":"Up","lines":[{"text":"DEVcon","left":830,"top":203,"width":151,"height":43,"word":[{"text":"DEVcon","left":830,"top":203,"width":151,"height":43,"confidence":288}]},{"text":"02.2019","left":853,"top":259,"width":100,"height":27,"word":[{"text":"02.2019","left":853,"top":259,"width":100,"height":27,"confidence":257}]},{"text":"—DEVCON-——","left":6,"top":685,"width":804,"height":93,"word":[{"text":"—DEVCON-——","left":6,"top":685,"width":804,"height":93,"confidence":294}]},{"text":"Nov20019","left":188,"top":802,"width":460,"height":92,"word":[{"text":"Nov20019","left":188,"top":802,"width":460,"height":92,"confidence":268}]},{"text":"22. 2019","left":185,"top":940,"width":376,"height":51,"word":[{"text":"22.","left":185,"top":941,"width":78,"height":49,"confidence":427},{"text":"2019","left":423,"top":940,"width":138,"height":51,"confidence":272}]}]}}],[],[{"region":{"language":"Arabic","orientation":"Up","lines":[{"text":"DEVcon","left":826,"top":193,"width":155,"height":44,"word":[{"text":"DEVcon","left":826,"top":193,"width":155,"height":44,"confidence":695}]},{"text":"02.2019","left":849,"top":251,"width":104,"height":28,"word":[{"text":"02.2019","left":849,"top":251,"width":104,"height":28,"confidence":701}]},{"text":"إديدولالا","left":57,"top":350,"width":306,"height":122,"word":[{"text":"إديدولالا","left":57,"top":350,"width":306,"height":122,"confidence":999}]},{"text":"NOV2QO19","left":188,"top":802,"width":461,"height":140,"word":[{"text":"NOV2QO19","left":188,"top":802,"width":461,"height":140,"confidence":495}]},{"text":"2019 .Yv .22","left":185,"top":940,"width":376,"height":99,"word":[{"text":".22","left":185,"top":940,"width":78,"height":50,"confidence":422},{"text":".Yv","left":263,"top":940,"width":143,"height":99,"confidence":422},{"text":"2019","left":423,"top":940,"width":138,"height":52,"confidence":701}]}]}},{"region":{"language":"Arabic","orientation":"Up","lines":[{"text":"لالالا إإ!! ،","left":1464,"top":225,"width":324,"height":126,"word":[{"text":"،","left":1464,"top":291,"width":13,"height":35,"confidence":999},{"text":"إإ!!","left":1543,"top":256,"width":109,"height":95,"confidence":999},{"text":"لالالا","left":1674,"top":225,"width":114,"height":88,"confidence":999}]},{"text":"أق","left":1523,"top":389,"width":283,"height":117,"word":[{"text":"أق","left":1523,"top":389,"width":283,"height":117,"confidence":999}]}]}}]]},{"start":70070,"duration":70070,"interval":14014,"events":[[{"region":{"language":"Spanish","orientation":"Up","lines":[{"text":"DEVcon","left":810,"top":194,"width":157,"height":38,"word":[{"text":"DEVcon","left":810,"top":194,"width":157,"height":38,"confidence":288}]},{"text":"02.2019","left":836,"top":251,"width":105,"height":25,"word":[{"text":"02.2019","left":836,"top":251,"width":105,"height":25,"confidence":306}]},{"text":"—DE CON--—","left":16,"top":704,"width":797,"height":107,"word":[{"text":"—DE","left":16,"top":716,"width":292,"height":95,"confidence":453},{"text":"CON--—","left":373,"top":704,"width":440,"height":99,"confidence":310}]},{"text":"22. Nov. 2019","left":203,"top":958,"width":377,"height":65,"word":[{"text":"22.","left":203,"top":972,"width":80,"height":51,"confidence":545},{"text":"Nov.","left":296,"top":968,"width":130,"height":51,"confidence":462},{"text":"2019","left":441,"top":958,"width":139,"height":55,"confidence":309}]}]}}],[{"region":{"language":"Spanish","orientation":"Up","lines":[{"text":"DEVcon","left":782,"top":197,"width":162,"height":40,"word":[{"text":"DEVcon","left":782,"top":197,"width":162,"height":40,"confidence":697}]},{"text":"02.2019","left":813,"top":251,"width":107,"height":30,"word":[{"text":"02.2019","left":813,"top":251,"width":107,"height":30,"confidence":283}]},{"text":"—DE","left":36,"top":765,"width":293,"height":102,"word":[{"text":"—DE","left":36,"top":765,"width":293,"height":102,"confidence":323}]},{"text":"22, Nov.","left":239,"top":1013,"width":223,"height":67,"word":[{"text":"22,","left":239,"top":1024,"width":85,"height":56,"confidence":332},{"text":"Nov.","left":333,"top":1013,"width":129,"height":54,"confidence":332}]}]}}],[{"region":{"language":"English","orientation":"Up","lines":[{"text":"Nov.","left":353,"top":1036,"width":129,"height":44,"word":[{"text":"Nov.","left":353,"top":1036,"width":129,"height":44,"confidence":274}]}]}}],[{"region":{"language":"Greek","orientation":"Down","lines":[{"text":"ΙΙΙ","left":159,"top":851,"width":114,"height":99,"word":[{"text":"ΙΙΙ","left":159,"top":851,"width":114,"height":99,"confidence":332}]}]}},{"region":{"language":"Greek","orientation":"Down","lines":[{"text":"6ιοτιο","left":998,"top":794,"width":105,"height":29,"word":[{"text":"6ιοτιο","left":998,"top":794,"width":105,"height":29,"confidence":297}]}]}}],[{"region":{"language":"German","orientation":"Up","lines":[{"text":"DEVcon","left":806,"top":227,"width":158,"height":36,"word":[{"text":"DEVcon","left":806,"top":227,"width":158,"height":36,"confidence":305}]},{"text":"02.2019","left":832,"top":283,"width":106,"height":24,"word":[{"text":"02.2019","left":832,"top":283,"width":106,"height":24,"confidence":292}]}]}}]]},{"start":140140,"duration":120000,"interval":120000,"events":[[{"region":{"language":"German","orientation":"Up","lines":[{"text":"DEVcon","left":801,"top":257,"width":159,"height":37,"word":[{"text":"DEVcon","left":801,"top":257,"width":159,"height":37,"confidence":697}]},{"text":"02.2019","left":829,"top":311,"width":106,"height":27,"word":[{"text":"02.2019","left":829,"top":311,"width":106,"height":27,"confidence":275}]}]}},{"region":{"language":"German","orientation":"Up","lines":[{"text":"onl","left":83,"top":565,"width":163,"height":84,"word":[{"text":"onl","left":83,"top":565,"width":163,"height":84,"confidence":309}]}]}}]]},{"start":260140,"duration":62182},{"start":322322,"duration":70070,"interval":14014,"events":[[{"region":{"language":"English","orientation":"Up","lines":[{"text":"DEVcon","left":1610,"top":172,"width":129,"height":34,"word":[{"text":"DEVcon","left":1610,"top":172,"width":129,"height":34,"confidence":698}]}]}}],[{"region":{"language":"English","orientation":"Up","lines":[{"text":"con","left":1755,"top":455,"width":58,"height":37,"word":[{"text":"con","left":1755,"top":455,"width":58,"height":37,"confidence":746}]}]}}],[{"region":{"language":"Arabic","orientation":"Down","lines":[{"text":"ي","left":1725,"top":280,"width":168,"height":59,"word":[{"text":"ي","left":1725,"top":280,"width":168,"height":59,"confidence":999}]}]}},{"region":{"language":"Arabic","orientation":"Down","lines":[{"text":"0ق٨دuo","left":262,"top":991,"width":129,"height":50,"word":[{"text":"0ق٨دuo","left":262,"top":991,"width":129,"height":50,"confidence":999}]}]}}],[{"region":{"language":"English","orientation":"Up","lines":[{"text":"O","left":521,"top":286,"width":40,"height":37,"word":[{"text":"O","left":521,"top":286,"width":40,"height":37,"confidence":470}]},{"text":"Michae' Scherer","left":395,"top":407,"width":196,"height":25,"word":[{"text":"Michae'","left":395,"top":407,"width":94,"height":24,"confidence":273},{"text":"Scherer","left":497,"top":409,"width":94,"height":23,"confidence":731}]},{"text":"Branjsa Stanojlo•","left":436,"top":450,"width":199,"height":31,"word":[{"text":"Branjsa","left":436,"top":450,"width":89,"height":23,"confidence":407},{"text":"Stanojlo•","left":534,"top":453,"width":101,"height":28,"confidence":300}]},{"text":"Frankfurt","left":385,"top":542,"width":108,"height":23,"word":[{"text":"Frankfurt","left":385,"top":542,"width":108,"height":23,"confidence":494}]},{"text":"Investment Banking","left":382,"top":603,"width":231,"height":27,"word":[{"text":"Investment","left":382,"top":603,"width":129,"height":20,"confidence":633},{"text":"Banking","left":521,"top":604,"width":92,"height":26,"confidence":255}]},{"text":"hoe! Scherer","left":418,"top":683,"width":141,"height":22,"word":[{"text":"hoe!","left":418,"top":683,"width":47,"height":20,"confidence":375},{"text":"Scherer","left":473,"top":684,"width":86,"height":21,"confidence":459}]},{"text":"-","left":380,"top":748,"width":5,"height":4,"word":[{"text":"-","left":380,"top":748,"width":5,"height":4,"confidence":532}]}]}}],[{"region":{"language":"English","orientation":"Up","lines":[{"text":"POMMERZBANK O","left":275,"top":312,"width":271,"height":38,"word":[{"text":"POMMERZBANK","left":275,"top":322,"width":221,"height":28,"confidence":267},{"text":"O","left":506,"top":312,"width":40,"height":37,"confidence":568}]},{"text":"Michael Scherer","left":389,"top":435,"width":193,"height":26,"word":[{"text":"Michael","left":389,"top":438,"width":93,"height":23,"confidence":799},{"text":"Scherer","left":490,"top":435,"width":92,"height":24,"confidence":845}]},{"text":"Branisa Stanoj\\o•","left":432,"top":475,"width":196,"height":28,"word":[{"text":"Branisa","left":432,"top":480,"width":89,"height":23,"confidence":695},{"text":"Stanoj\\o•","left":529,"top":475,"width":99,"height":28,"confidence":385}]},{"text":"Frankfurt","left":387,"top":572,"width":108,"height":24,"word":[{"text":"Frankfurt","left":387,"top":572,"width":108,"height":24,"confidence":714}]},{"text":"Investment Banking","left":387,"top":628,"width":229,"height":26,"word":[{"text":"Investment","left":387,"top":633,"width":129,"height":21,"confidence":765},{"text":"Banking","left":525,"top":628,"width":91,"height":24,"confidence":673}]},{"text":"Bent Schult","left":386,"top":683,"width":131,"height":24,"word":[{"text":"Bent","left":386,"top":688,"width":53,"height":19,"confidence":559},{"text":"Schult","left":448,"top":683,"width":69,"height":22,"confidence":506}]},{"text":"Michael Scherer","left":386,"top":711,"width":182,"height":23,"word":[{"text":"Michael","left":386,"top":713,"width":88,"height":21,"confidence":493},{"text":"Scherer","left":482,"top":711,"width":86,"height":20,"confidence":674}]},{"text":"- (2019)","left":388,"top":764,"width":202,"height":24,"word":[{"text":"-","left":388,"top":781,"width":9,"height":4,"confidence":772},{"text":"(2019)","left":522,"top":764,"width":68,"height":24,"confidence":259}]}]}}]]},{"start":392392,"duration":70070,"interval":14014,"events":[[{"region":{"language":"English","orientation":"Up","lines":[{"text":".","left":453,"top":67,"width":9,"height":7,"word":[{"text":".","left":453,"top":67,"width":9,"height":7,"confidence":437}]}]}},{"region":{"language":"English","orientation":"Up","lines":[{"text":"Brarusa","left":28,"top":272,"width":63,"height":15,"word":[{"text":"Brarusa","left":28,"top":272,"width":63,"height":15,"confidence":351}]},{"text":"20 t","left":169,"top":510,"width":24,"height":14,"word":[{"text":"20","left":169,"top":510,"width":18,"height":14,"confidence":267},{"text":"t","left":189,"top":511,"width":4,"height":11,"confidence":267}]}]}},{"region":{"language":"English","orientation":"Up","lines":[{"text":"POMMERZBANK O","left":289,"top":288,"width":269,"height":37,"word":[{"text":"POMMERZBANK","left":289,"top":289,"width":219,"height":30,"confidence":276},{"text":"O","left":518,"top":288,"width":40,"height":37,"confidence":655}]},{"text":"Michael Scherer","left":394,"top":409,"width":193,"height":25,"word":[{"text":"Michael","left":394,"top":409,"width":93,"height":22,"confidence":879},{"text":"Scherer","left":495,"top":410,"width":92,"height":24,"confidence":994}]},{"text":"Branisa Stanojlo.","left":435,"top":452,"width":199,"height":30,"word":[{"text":"Branisa","left":435,"top":452,"width":88,"height":22,"confidence":696},{"text":"Stanojlo.","left":531,"top":454,"width":103,"height":28,"confidence":414}]},{"text":"Frankfurt","left":384,"top":543,"width":109,"height":22,"word":[{"text":"Frankfurt","left":384,"top":543,"width":109,"height":22,"confidence":825}]},{"text":"Investment Banking","left":381,"top":602,"width":229,"height":28,"word":[{"text":"Investment","left":381,"top":602,"width":129,"height":21,"confidence":817},{"text":"Banking","left":518,"top":603,"width":92,"height":27,"confidence":993}]},{"text":"Berit Schult","left":378,"top":654,"width":130,"height":20,"word":[{"text":"Berit","left":378,"top":654,"width":53,"height":19,"confidence":610},{"text":"Schult","left":439,"top":655,"width":69,"height":19,"confidence":487}]},{"text":"Michael Scherer","left":376,"top":682,"width":180,"height":20,"word":[{"text":"Michael","left":376,"top":682,"width":87,"height":20,"confidence":497},{"text":"Scherer","left":471,"top":683,"width":85,"height":19,"confidence":833}]},{"text":"- 300000 (2019)","left":373,"top":738,"width":202,"height":23,"word":[{"text":"-","left":373,"top":745,"width":11,"height":5,"confidence":515},{"text":"300000","left":393,"top":738,"width":87,"height":20,"confidence":345},{"text":"(2019)","left":507,"top":740,"width":68,"height":21,"confidence":272}]}]}}],[{"region":{"language":"English","orientation":"Up","lines":[{"text":".","left":442,"top":80,"width":9,"height":7,"word":[{"text":".","left":442,"top":80,"width":9,"height":7,"confidence":289}]}]}},{"region":{"language":"English","orientation":"Up","lines":[{"text":"B' Sta","left":25,"top":292,"width":95,"height":16,"word":[{"text":"B'","left":25,"top":292,"width":17,"height":15,"confidence":250},{"text":"Sta","left":92,"top":292,"width":28,"height":16,"confidence":431}]}]}},{"region":{"language":"English","orientation":"Up","lines":[{"text":"O","left":512,"top":299,"width":39,"height":36,"word":[{"text":"O","left":512,"top":299,"width":39,"height":36,"confidence":594}]},{"text":"Michael Scherer","left":391,"top":420,"width":192,"height":22,"word":[{"text":"Michael","left":391,"top":420,"width":93,"height":22,"confidence":860},{"text":"Scherer","left":492,"top":421,"width":91,"height":21,"confidence":898}]},{"text":"Branisa Stanoflo•.","left":433,"top":463,"width":198,"height":27,"word":[{"text":"Branisa","left":433,"top":463,"width":87,"height":21,"confidence":563},{"text":"Stanoflo•.","left":529,"top":463,"width":102,"height":27,"confidence":394}]},{"text":"Frankfurt","left":385,"top":553,"width":107,"height":22,"word":[{"text":"Frankfurt","left":385,"top":553,"width":107,"height":22,"confidence":737}]},{"text":"Investment Banking","left":382,"top":612,"width":227,"height":26,"word":[{"text":"Investment","left":382,"top":614,"width":128,"height":18,"confidence":762},{"text":"Banking","left":519,"top":612,"width":90,"height":26,"confidence":991}]},{"text":"Berit Schult","left":380,"top":664,"width":129,"height":20,"word":[{"text":"Berit","left":380,"top":665,"width":54,"height":19,"confidence":616},{"text":"Schult","left":441,"top":664,"width":68,"height":20,"confidence":554}]},{"text":"Michael Scherer","left":379,"top":692,"width":179,"height":19,"word":[{"text":"Michael","left":379,"top":692,"width":86,"height":19,"confidence":537},{"text":"Scherer","left":473,"top":692,"width":85,"height":19,"confidence":730}]},{"text":"- 300.000 (2019)","left":380,"top":747,"width":199,"height":22,"word":[{"text":"-","left":380,"top":757,"width":8,"height":4,"confidence":869},{"text":"300.000","left":397,"top":748,"width":87,"height":20,"confidence":391},{"text":"(2019)","left":510,"top":747,"width":69,"height":22,"confidence":265}]}]}}],[{"region":{"language":"English","orientation":"Up","lines":[{"text":".","left":437,"top":88,"width":9,"height":7,"word":[{"text":".","left":437,"top":88,"width":9,"height":7,"confidence":350}]},{"text":"O","left":508,"top":305,"width":39,"height":36,"word":[{"text":"O","left":508,"top":305,"width":39,"height":36,"confidence":589}]},{"text":"Michael Scherer","left":390,"top":426,"width":190,"height":23,"word":[{"text":"Michael","left":390,"top":426,"width":91,"height":23,"confidence":849},{"text":"Scherer","left":489,"top":426,"width":91,"height":22,"confidence":864}]},{"text":"Branisa Stanojlm","left":432,"top":468,"width":196,"height":26,"word":[{"text":"Branisa","left":432,"top":469,"width":86,"height":20,"confidence":597},{"text":"Stanojlm","left":527,"top":468,"width":101,"height":26,"confidence":416}]},{"text":"20 t","left":170,"top":535,"width":24,"height":14,"word":[{"text":"20","left":170,"top":535,"width":18,"height":14,"confidence":278},{"text":"t","left":190,"top":535,"width":4,"height":11,"confidence":278}]},{"text":"Frankfurt","left":385,"top":559,"width":106,"height":21,"word":[{"text":"Frankfurt","left":385,"top":559,"width":106,"height":21,"confidence":886}]},{"text":"Investment Banking","left":382,"top":616,"width":226,"height":24,"word":[{"text":"Investment","left":382,"top":619,"width":128,"height":19,"confidence":855},{"text":"Banking","left":518,"top":616,"width":90,"height":24,"confidence":594}]},{"text":"iii","left":297,"top":667,"width":50,"height":47,"word":[{"text":"iii","left":297,"top":667,"width":50,"height":47,"confidence":454}]},{"text":"Berit Schult","left":381,"top":669,"width":128,"height":20,"word":[{"text":"Berit","left":381,"top":670,"width":52,"height":19,"confidence":668},{"text":"Schult","left":442,"top":669,"width":67,"height":19,"confidence":445}]},{"text":"Michael Scherer","left":380,"top":696,"width":178,"height":20,"word":[{"text":"Michael","left":380,"top":697,"width":86,"height":19,"confidence":538},{"text":"Scherer","left":474,"top":696,"width":84,"height":19,"confidence":830}]},{"text":"300.000 € (2019)","left":399,"top":750,"width":180,"height":22,"word":[{"text":"300.000","left":399,"top":752,"width":86,"height":19,"confidence":519},{"text":"€","left":492,"top":752,"width":13,"height":18,"confidence":474},{"text":"(2019)","left":511,"top":750,"width":68,"height":22,"confidence":363}]}]}}],[{"region":{"language":"ChineseTraditional","orientation":"Down","lines":[{"text":"( 6100 ) ) 0£一","left":1334,"top":288,"width":198,"height":28,"word":[{"text":"(","left":1334,"top":296,"width":6,"height":20,"confidence":489},{"text":"6100","left":1341,"top":293,"width":60,"height":23,"confidence":329},{"text":")","left":1408,"top":294,"width":12,"height":18,"confidence":403},{"text":")","left":1459,"top":291,"width":8,"height":18,"confidence":639},{"text":"0","left":1487,"top":289,"width":13,"height":17,"confidence":576},{"text":"£","left":1501,"top":288,"width":12,"height":18,"confidence":365},{"text":"一","left":1522,"top":294,"width":10,"height":4,"confidence":754}]},{"text":"u u","left":1416,"top":421,"width":111,"height":20,"word":[{"text":"u","left":1416,"top":427,"width":14,"height":14,"confidence":429},{"text":"u","left":1513,"top":421,"width":14,"height":15,"confidence":368}]},{"text":"e」9","left":1453,"top":570,"width":38,"height":20,"word":[{"text":"e","left":1453,"top":571,"width":13,"height":16,"confidence":432},{"text":"」","left":1465,"top":572,"width":9,"height":14,"confidence":272},{"text":"9","left":1476,"top":570,"width":15,"height":20,"confidence":339}]},{"text":")","left":1495,"top":611,"width":10,"height":16,"word":[{"text":")","left":1495,"top":611,"width":10,"height":16,"confidence":602}]}]}}],[{"region":{"language":"English","orientation":"Up","lines":[{"text":"Sta","left":101,"top":279,"width":28,"height":17,"word":[{"text":"Sta","left":101,"top":279,"width":28,"height":17,"confidence":361}]}]}},{"region":{"language":"English","orientation":"Up","lines":[{"text":"FOMMERZBANK O","left":289,"top":294,"width":263,"height":36,"word":[{"text":"FOMMERZBANK","left":289,"top":295,"width":215,"height":28,"confidence":253},{"text":"O","left":513,"top":294,"width":39,"height":36,"confidence":616}]},{"text":"Michael Scherer","left":392,"top":412,"width":188,"height":24,"word":[{"text":"Michael","left":392,"top":412,"width":91,"height":22,"confidence":782},{"text":"Scherer","left":491,"top":414,"width":89,"height":22,"confidence":674}]}]}},{"region":{"language":"English","orientation":"Up","lines":[{"text":"Branisa Stan0Jlo•.","left":432,"top":454,"width":196,"height":30,"word":[{"text":"Branisa","left":432,"top":454,"width":86,"height":21,"confidence":695},{"text":"Stan0Jlo•.","left":526,"top":456,"width":102,"height":28,"confidence":341}]},{"text":"Start","left":46,"top":513,"width":36,"height":14,"word":[{"text":"Start","left":46,"top":513,"width":36,"height":14,"confidence":291}]},{"text":"Frankfurt","left":383,"top":542,"width":106,"height":22,"word":[{"text":"Frankfurt","left":383,"top":542,"width":106,"height":22,"confidence":810}]},{"text":"Investment Banking","left":379,"top":600,"width":223,"height":28,"word":[{"text":"Investment","left":379,"top":600,"width":126,"height":21,"confidence":633},{"text":"Banking","left":513,"top":603,"width":89,"height":25,"confidence":825}]},{"text":"Berit Schult","left":376,"top":651,"width":127,"height":20,"word":[{"text":"Berit","left":376,"top":651,"width":52,"height":19,"confidence":482},{"text":"Schult","left":437,"top":652,"width":66,"height":19,"confidence":430}]},{"text":"Michael Scherer","left":375,"top":679,"width":175,"height":20,"word":[{"text":"Michael","left":375,"top":679,"width":85,"height":19,"confidence":815},{"text":"Scherer","left":467,"top":680,"width":83,"height":19,"confidence":986}]},{"text":"300000 €","left":391,"top":734,"width":106,"height":19,"word":[{"text":"300000","left":391,"top":734,"width":86,"height":19,"confidence":261},{"text":"€","left":483,"top":735,"width":14,"height":17,"confidence":261}]}]}}]]},{"start":462462,"duration":28028},{"start":490490,"duration":70070,"interval":14014,"events":[[{"region":{"language":"Portuguese","orientation":"Up","lines":[{"text":"nnii","left":1303,"top":775,"width":166,"height":80,"word":[{"text":"nnii","left":1303,"top":775,"width":166,"height":80,"confidence":273}]}]}}],[],[{"region":{"language":"ChineseTraditional","orientation":"Down","lines":[{"text":"6 0 0","left":1448,"top":605,"width":177,"height":51,"word":[{"text":"6","left":1448,"top":605,"width":26,"height":38,"confidence":556},{"text":"0","left":1501,"top":609,"width":26,"height":39,"confidence":705},{"text":"0","left":1597,"top":616,"width":28,"height":40,"confidence":696}]},{"text":"u 0 Q","left":1409,"top":672,"width":265,"height":88,"word":[{"text":"u","left":1409,"top":672,"width":37,"height":47,"confidence":432},{"text":"0","left":1453,"top":678,"width":39,"height":46,"confidence":888},{"text":"Q","left":1622,"top":697,"width":52,"height":63,"confidence":567}]}]}}],[{"region":{"language":"Japanese","orientation":"Left","lines":[{"text":"D Evcoコ","left":689,"top":265,"width":97,"height":259,"word":[{"text":"D","left":723,"top":265,"width":63,"height":51,"confidence":539},{"text":"Evco","left":696,"top":324,"width":81,"height":157,"confidence":347},{"text":"コ","left":689,"top":489,"width":47,"height":35,"confidence":721}]},{"text":"02.20一9","left":625,"top":310,"width":57,"height":173,"word":[{"text":"02.20","left":631,"top":310,"width":51,"height":121,"confidence":836},{"text":"一","left":628,"top":435,"width":37,"height":15,"confidence":685},{"text":"9","left":625,"top":458,"width":38,"height":25,"confidence":948}]},{"text":"朝第第■","left":130,"top":1271,"width":474,"height":76,"word":[{"text":"朝","left":130,"top":1271,"width":79,"height":58,"confidence":407},{"text":"第","left":290,"top":1282,"width":70,"height":53,"confidence":265},{"text":"第","left":456,"top":1288,"width":67,"height":54,"confidence":270},{"text":"■","left":532,"top":1292,"width":72,"height":55,"confidence":588}]},{"text":"ロロロロ","left":93,"top":1448,"width":531,"height":88,"word":[{"text":"ロ","left":93,"top":1448,"width":88,"height":70,"confidence":841},{"text":"ロ","left":182,"top":1454,"width":84,"height":67,"confidence":592},{"text":"ロ","left":271,"top":1457,"width":81,"height":68,"confidence":984},{"text":"ロ","left":543,"top":1466,"width":81,"height":70,"confidence":682}]}]}}],[{"region":{"language":"Japanese","orientation":"Down","lines":[{"text":"ロロロロ","left":393,"top":98,"width":86,"height":525,"word":[{"text":"ロ","left":410,"top":98,"width":69,"height":89,"confidence":906},{"text":"ロ","left":407,"top":188,"width":67,"height":82,"confidence":641},{"text":"ロ","left":403,"top":275,"width":68,"height":79,"confidence":892},{"text":"ロ","left":393,"top":542,"width":69,"height":81,"confidence":794}]},{"text":"ヨ一0■","left":705,"top":159,"width":56,"height":288,"word":[{"text":"ヨ","left":712,"top":159,"width":49,"height":73,"confidence":576},{"text":"一","left":711,"top":231,"width":23,"height":7,"confidence":749},{"text":"0","left":708,"top":304,"width":47,"height":65,"confidence":327},{"text":"■","left":705,"top":383,"width":48,"height":64,"confidence":337}]},{"text":"6 0 0","left":1431,"top":624,"width":170,"height":56,"word":[{"text":"6","left":1431,"top":624,"width":23,"height":37,"confidence":916},{"text":"0","left":1482,"top":630,"width":24,"height":37,"confidence":760},{"text":"0","left":1574,"top":640,"width":27,"height":40,"confidence":813}]},{"text":"u0 ) ^ヨ0","left":1390,"top":686,"width":254,"height":96,"word":[{"text":"u0","left":1390,"top":686,"width":79,"height":53,"confidence":498},{"text":")","left":1472,"top":699,"width":31,"height":45,"confidence":456},{"text":"^","left":1503,"top":706,"width":47,"height":61,"confidence":785},{"text":"ヨ","left":1551,"top":710,"width":35,"height":63,"confidence":922},{"text":"0","left":1596,"top":720,"width":48,"height":62,"confidence":277}]}]}}]]},{"start":560560,"duration":42042},{"start":602602,"duration":70070,"interval":14014,"events":[[{"region":{"language":"Japanese","orientation":"Right","lines":[{"text":"日つ","left":119,"top":1555,"width":904,"height":192,"word":[{"text":"日","left":119,"top":1558,"width":106,"height":189,"confidence":315},{"text":"つ","left":875,"top":1555,"width":148,"height":133,"confidence":483}]},{"text":"ロロ","left":119,"top":1743,"width":222,"height":130,"word":[{"text":"ロ","left":119,"top":1753,"width":106,"height":120,"confidence":944},{"text":"ロ","left":236,"top":1743,"width":105,"height":121,"confidence":817}]}]}}],[],[{"region":{"language":"Arabic","orientation":"Up","lines":[{"text":"اأوا لاه .","left":1463,"top":372,"width":377,"height":169,"word":[{"text":".","left":1463,"top":372,"width":10,"height":169,"confidence":999},{"text":"لاه","left":1493,"top":372,"width":139,"height":169,"confidence":999},{"text":"اأوا","left":1652,"top":372,"width":188,"height":169,"confidence":999}]},{"text":"إالاى","left":1678,"top":544,"width":120,"height":80,"word":[{"text":"إالاى","left":1678,"top":544,"width":120,"height":80,"confidence":999}]}]}}],[],[{"region":{"language":"Arabic","orientation":"Up","lines":[{"text":"إإلالاى","left":1698,"top":544,"width":146,"height":89,"word":[{"text":"إإلالاى","left":1698,"top":544,"width":146,"height":89,"confidence":999}]}]}}]]},{"start":672672,"duration":70070,"interval":70070,"events":[[{"region":{"language":"Arabic","orientation":"Up","lines":[{"text":"اتة","left":1395,"top":446,"width":248,"height":175,"word":[{"text":"اتة","left":1395,"top":446,"width":248,"height":175,"confidence":999}]},{"text":"لآ0.","left":1351,"top":620,"width":230,"height":204,"word":[{"text":"لآ0.","left":1351,"top":620,"width":230,"height":204,"confidence":999}]}]}}]]},{"start":742742,"duration":120000,"interval":120000,"events":[[{"region":{"language":"ChineseTraditional","orientation":"Left","lines":[{"text":"Deka","left":182,"top":1054,"width":35,"height":69,"word":[{"text":"Deka","left":182,"top":1054,"width":35,"height":69,"confidence":295}]}]}}]]},{"start":862742,"duration":62182},{"start":924924,"duration":120000,"interval":120000,"events":[[{"region":{"language":"Arabic","orientation":"Up","lines":[{"text":"؟","left":1341,"top":383,"width":206,"height":148,"word":[{"text":"؟","left":1341,"top":383,"width":206,"height":148,"confidence":999}]}]}}]]},{"start":1044924,"duration":300420},{"start":1345344,"duration":56056,"interval":56056,"events":[[{"region":{"language":"Arabic","orientation":"Down","lines":[{"text":"ي","left":1229,"top":781,"width":186,"height":102,"word":[{"text":"ي","left":1229,"top":781,"width":186,"height":102,"confidence":999}]}]}}]]},{"start":1401400,"duration":120000,"interval":120000,"events":[[{"region":{"language":"Korean","orientation":"Left","lines":[{"text":"4/4 //쳔牙","left":0,"top":1584,"width":519,"height":218,"word":[{"text":"4/4","left":0,"top":1611,"width":120,"height":191,"confidence":424},{"text":"//쳔牙","left":240,"top":1584,"width":279,"height":171,"confidence":455}]}]}}]]},{"start":1521400,"duration":482602},{"start":2004002,"duration":14014,"interval":14014,"events":[[{"region":{"language":"Arabic","orientation":"Down","lines":[{"text":"سلاح","left":1026,"top":0,"width":219,"height":84,"word":[{"text":"سلاح","left":1026,"top":0,"width":219,"height":84,"confidence":999}]},{"text":"-","left":1009,"top":142,"width":138,"height":124,"word":[{"text":"-","left":1009,"top":142,"width":138,"height":124,"confidence":999}]},{"text":"ر","left":927,"top":404,"width":213,"height":162,"word":[{"text":"ر","left":927,"top":404,"width":213,"height":162,"confidence":999}]},{"text":"اق تك","left":14,"top":440,"width":554,"height":119,"word":[{"text":"تك","left":14,"top":456,"width":198,"height":103,"confidence":999},{"text":"اق","left":251,"top":440,"width":317,"height":119,"confidence":999}]},{"text":"تعا أتات","left":13,"top":477,"width":974,"height":228,"word":[{"text":"أتات","left":13,"top":570,"width":197,"height":93,"confidence":999},{"text":"تعا","left":241,"top":477,"width":746,"height":228,"confidence":999}]},{"text":"لاE■ ت■ قم","left":111,"top":636,"width":1167,"height":158,"word":[{"text":"قم","left":111,"top":676,"width":96,"height":96,"confidence":999},{"text":"ت■","left":447,"top":636,"width":184,"height":158,"confidence":999},{"text":"لاE■","left":726,"top":636,"width":552,"height":158,"confidence":999}]},{"text":"ملا حانات 4-معت","left":237,"top":704,"width":1294,"height":182,"word":[{"text":"4-معت","left":237,"top":769,"width":462,"height":102,"confidence":999},{"text":"حانات","left":736,"top":704,"width":416,"height":182,"confidence":999},{"text":"ملا","left":1217,"top":750,"width":314,"height":129,"confidence":999}]},{"text":"اتإإم تا لال ـنحبيرسما","left":131,"top":860,"width":1413,"height":213,"word":[{"text":"ـنحبيرسما","left":131,"top":908,"width":571,"height":165,"confidence":999},{"text":"لال","left":741,"top":860,"width":174,"height":213,"confidence":999},{"text":"تا","left":1002,"top":860,"width":116,"height":213,"confidence":999},{"text":"اتإإم","left":1138,"top":860,"width":406,"height":213,"confidence":999}]}]}},{"region":{"language":"Arabic","orientation":"Down","lines":[{"text":"هآ","left":1673,"top":894,"width":130,"height":130,"word":[{"text":"هآ","left":1673,"top":894,"width":130,"height":130,"confidence":999}]}]}}]]},{"start":2018016,"duration":24984,"interval":24984,"events":[[{"region":{"language":"Arabic","orientation":"Down","lines":[{"text":"ؤم","left":1007,"top":400,"width":149,"height":124,"word":[{"text":"ؤم","left":1007,"top":400,"width":149,"height":124,"confidence":999}]},{"text":"وثه","left":1217,"top":620,"width":316,"height":253,"word":[{"text":"وثه","left":1217,"top":620,"width":316,"height":253,"confidence":999}]},{"text":"عبييهح لا","left":52,"top":924,"width":567,"height":156,"word":[{"text":"لا","left":52,"top":924,"width":144,"height":156,"confidence":999},{"text":"عبييهح","left":214,"top":924,"width":405,"height":156,"confidence":999}]}]}}]]}]}